_polar_lib.abi3.so
oso/exceptions.py
oso/__init__.py
oso/oso.py
oso/__main__.py
oso/py.typed
oso.libs/libgcc_s-a04fdf82.so.1
oso-0.27.3.dist-info/WHEEL
oso-0.27.3.dist-info/RECORD
oso-0.27.3.dist-info/top_level.txt
oso-0.27.3.dist-info/METADATA
polar/exceptions.py
polar/build.py
polar/predicate.py
polar/partial.py
polar/ffi.py
polar/polar.py
polar/variable.py
polar/__init__.py
polar/expression.py
polar/query.py
polar/data_filtering.py
polar/__main__.py
polar/host.py
polar/errors.py
polar/py.typed
polar/data/__init__.py
polar/data/filter.py
polar/data/adapter/__init__.py
polar/data/adapter/adapter.py
polar/data/adapter/sqlalchemy_adapter.py
