Metadata-Version: 2.1
Name: oso
Version: 0.27.3
Summary: oso is an open source policy engine for authorization that's embedded in your application
Author: Oso Security, Inc.
Classifier: Development Status :: 4 - Beta
Classifier: Programming Language :: Python :: 3.7
Classifier: License :: OSI Approved :: Apache Software License
Requires-Python: >=3.7
Requires-Dist: cffi ~=1.15
Requires-Dist: dataclasses ; python_version < "3.7"
Provides-Extra: django
Provides-Extra: flask
Requires-Dist: flask ; extra == 'flask'
Requires-Dist: authlib ; extra == 'flask'
Provides-Extra: jwt
Requires-Dist: authlib ; extra == 'jwt'
